pybrowsers/__main__.py
pybrowsers_profiles-0.0.13.dist-info/METADATA
pybrowsers_profiles-0.0.13.dist-info/WHEEL
pybrowsers_profiles-0.0.13.dist-info/entry_points.txt
pybrowsers_profiles-0.0.13.dist-info/licenses/LICENSE.txt
pybrowsers_profiles-0.0.13.dist-info/RECORD
