Metadata-Version: 2.3
Name: pybrowsers-profiles
Version: 0.0.13
Summary: Simple script for manage browser's profiles.
Project-URL: Homepage, https://github.com/haaag/PyBrowsers-Profiles
Project-URL: Bug Tracker, https://github.com/haaag/PyBrowsers-Profiles/issues
Author-email: haaag <git.haaag@gmail.com>
License: MIT License
License-File: LICENSE.txt
Keywords: dmenu,firefox,librewolf,profiles,rofi
Classifier: Programming Language :: Python :: 3.9
Classifier: Programming Language :: Python :: 3.10
Classifier: Programming Language :: Python :: 3.11
Classifier: Programming Language :: Python :: 3.12
Requires-Python: >=3.9
Requires-Dist: pyselector>=0.0.25
